Metadata-Version: 2.1
Name: basata
Version: 1.0.11
Summary: BASATA - Code less while gaining more
Home-page: https://github.com/sg-tarek/BASATA
Author: Tarek K. Ghanoum
Author-email: ta.ghanoum@gmail.com
License: MIT
Project-URL: Documentation, https://sg-tarek.github.io/
Keywords: ML AI Supervised TimeSeries Unsupservised NLP
Platform: UNKNOWN
Classifier: Development Status :: 3 - Alpha
Classifier: Intended Audience :: Developers
Classifier: License :: OSI Approved :: MIT License
Classifier: Programming Language :: Python :: 3
License-File: LICENSE.txt
